Metadata-Version: 1.0
Name: zendesk-redactor
Version: 0.0.3
Summary: A command-line interface for Zendesk Ticket Redaction app
Home-page: https://github.com/Ch00k/zendesk-redactor
Author: Andrii Yurchuk
Author-email: ay@mntw.re
License: Unlicense
Keywords: zendesk api ticket redaction
Platform: UNKNOWN
